SQL_multisearch/SQL_multisearch.py
SQL_multisearch/__init__.py
SQL_multisearch-1.0.4.dist-info/LICENSE.txt
SQL_multisearch-1.0.4.dist-info/METADATA
SQL_multisearch-1.0.4.dist-info/WHEEL
SQL_multisearch-1.0.4.dist-info/top_level.txt
SQL_multisearch-1.0.4.dist-info/RECORD
