Metadata-Version: 2.1
Name: SQL-multisearch
Version: 1.0.4
Summary: SQL search and ranking engine in multiple fields of database table
Home-page: UNKNOWN
Author: Maxime Challon
Author-email: maxime.challon@gmail.com
License: UNKNOWN
Keywords: SQL search ranking sqlite
Platform: UNKNOWN
Classifier: Intended Audience :: Developers
Classifier: License :: OSI Approved :: MIT License
Classifier: Natural Language :: English
Classifier: Programming Language :: Python :: 3.7
Classifier: Topic :: Education
Requires-Dist: sqlalchemy
